PhigrosAPILib/Cli.py
PhigrosAPILib/Core.py
PhigrosAPILib/Important.py
PhigrosAPILib/Updater.py
PhigrosAPILib/__init__.py
PhigrosAPILib/PyTypes/Best.py
PhigrosAPILib/PyTypes/Player.py
PhigrosAPILib/PyTypes/Profile.py
PhigrosAPILib/PyTypes/Progress.py
PhigrosAPILib/PyTypes/Record.py
PhigrosAPILib/PyTypes/SongInfo.py
PhigrosAPILib/PyTypes/Summary.py
PhigrosAPILib/PyTypes/__init__.py
PhigrosAPILib/Tools/ByteReader.py
PhigrosAPILib/Tools/DecryptSave.py
PhigrosAPILib/Tools/LoadJson.py
PhigrosAPILib/Tools/ReadFile.py
PhigrosAPILib/Tools/__init__.py
PhigrosAPILib/data/constants.json
PhigrosAPILib/data/infos.json
PhigrosAPILib-1.3.1.dist-info/LICENSE
PhigrosAPILib-1.3.1.dist-info/METADATA
PhigrosAPILib-1.3.1.dist-info/WHEEL
PhigrosAPILib-1.3.1.dist-info/entry_points.txt
PhigrosAPILib-1.3.1.dist-info/top_level.txt
PhigrosAPILib-1.3.1.dist-info/RECORD
